davidkhala/ml/ocr/__init__.py
davidkhala/ml/ocr/interface.py
davidkhala/ml/ocr/paddle/__init__.py
davidkhala/ml/ocr/paddle/ie.py
davidkhala_ml_ocr-0.0.3.dist-info/METADATA
davidkhala_ml_ocr-0.0.3.dist-info/WHEEL
davidkhala_ml_ocr-0.0.3.dist-info/RECORD
