Metadata-Version: 2.4
Name: davidkhala.ml.ocr
Version: 0.0.3
Requires-Python: >=3.10
Requires-Dist: davidkhala-utils
Requires-Dist: pydantic
Provides-Extra: paddle
Requires-Dist: paddleocr; extra == 'paddle'
Requires-Dist: paddlepaddle==3.2.*; extra == 'paddle'
Provides-Extra: paddle-ocr
Requires-Dist: aistudio-sdk==0.2.6; extra == 'paddle-ocr'
Requires-Dist: paddlenlp==3.0.0b4; (python_version < '3.12') and extra == 'paddle-ocr'
Requires-Dist: pip; extra == 'paddle-ocr'
Requires-Dist: setuptools; extra == 'paddle-ocr'
